Workbook

Sheet ROI Model
A1: MERIDIAN RETAIL GROUP — Omnichannel Platform ROI Hypothesis
A3: Assumption | B3: Pessimistic | C3: Base | D3: Optimistic
A4: Estimated annual digital GMV across 22 countries ($M) | B4: 2500 | C4: 4000 | D4: 6000
A5: Cross-channel revenue uplift (%) | B5: 0.03 | C5: 0.07 | D5: 0.12
A6: Marketing waste reduction (%) | B6: 0.05 | C6: 0.12 | D6: 0.22
A7: IT ops cost reduction (%) | B7: 0.08 | C7: 0.15 | D7: 0.25
A8: Loyalty member CLV increase (%) | B8: 0.1 | C8: 0.2 | D8: 0.35
A9: Regulatory fine avoidance ($M) | B9: 5 | C9: 25 | D9: 100
A10: Current annual marketing spend ($M) | B10: 300 | C10: 500 | D10: 750
A11: Current annual IT ops spend ($M) | B11: 80 | C11: 120 | D11: 180
A12: Total program investment ($M) | B12: 42 | C12: 42 | D12: 42
A14: BENEFIT CALCULATIONS (Annual, Year 2 Steady State)
A15: Benefit Stream | B15: Pessimistic | C15: Base | D15: Optimistic
A16: Revenue uplift (cross-channel) | B16: =B4*B5 | C16: =C4*C5 | D16: =D4*D5
A17: Marketing waste recovery | B17: =B10*B6 | C17: =C10*C6 | D17: =D10*D6
A18: IT ops cost reduction | B18: =B11*B7 | C18: =C11*C7 | D18: =D11*D7
A19: Loyalty CLV increase | B19: =B4*0.4*B8 | C19: =C4*0.4*C8 | D19: =D4*0.4*D8
A20: Regulatory fine avoidance | B20: =B9 | C20: =C9 | D20: =D9
A21: TOTAL ANNUAL BENEFIT (Year 2+) | B21: =SUM(B16:B20) | C21: =SUM(C16:C20) | D21: =SUM(D16:D20)
A23: 5-YEAR ROI SUMMARY
A24: Metric | B24: Pessimistic | C24: Base | D24: Optimistic
A25: Year 1 (ramp-up): Benefit ($M) | B25: =B21*0.3 | C25: =C21*0.3 | D25: =D21*0.3
A26: Year 2: Benefit ($M) | B26: =B21*0.8 | C26: =C21*0.8 | D26: =D21*0.8
A27: Year 3+: Benefit ($M) | B27: =B21 | C27: =C21 | D27: =D21
A28: Total 5-Year Benefit ($M) | B28: =B25*0.3+B26*0.8+B27*3 | C28: =C25*0.3+C26*0.8+C27*3 | D28: =D25*0.3+D26*0.8+D27*3
A29: Net 5-Year Benefit (After $42M Investment) | B29: =B28-42.0 | C29: =C28-42 | D29: =D28-42
A30: ROI Ratio (Total Benefit / Investment) | B30: =B28/42 | C30: =C28/42 | D30: =D28/42
A31: Payback Period (Years) | B31: =42/(B21*0.8) | C31: =42/(C21*0.8) | D31: =42/(D21*0.8)

Sheet Sensitivity
A1: KEY VARIABLE SENSITIVITY — Base Scenario
A3: Variable | B3: -25% Change in Variable | C3: +25% Change in Variable
A4: Cross-channel revenue uplift % | B4: =(C4*C5*0.75+'ROI Model'!C21-C4*C5) | C4: =(C4*C5*1.25+'ROI Model'!C21-C4*C5)
A5: Marketing waste recovery % | B5: =(C10*C6*0.75+'ROI Model'!C21-C10*C6) | C5: =(C10*C6*1.25+'ROI Model'!C21-C10*C6)
A6: IT ops cost reduction % | B6: =(C11*C7*0.75+'ROI Model'!C21-C11*C7) | C6: =(C11*C7*1.25+'ROI Model'!C21-C11*C7)
A7: Loyalty CLV increase % | B7: =(C4*0.4*C8*0.75+'ROI Model'!C21-C4*0.4*C8) | C7: =(C4*0.4*C8*1.25+'ROI Model'!C21-C4*0.4*C8)
A8: Total program investment | B8: =('ROI Model'!C21-42*0.75) | C8: =('ROI Model'!C21-42*1.25)

Sheet Investment Phasing
A1: PROGRAM INVESTMENT PHASING ($42M)
A3: Phase | B3: Duration | C3: Scope | D3: Budget ($M) | E3: % of Total
A4: Phase 0: Foundation & Pilot | B4: Months 1–3 | C4: CMP + CIAM + Data audit + POC country | D4: 6 | E4: 0.143
A5: Phase 1: Core Services | B5: Months 4–9 | C5: Unified profile + Loyalty engine + Cart service + OAuth 2.0 | D5: 12 | E5: 0.286
A6: Phase 2: Country Rollouts (8–10 countries) | B6: Months 7–14 | C6: Headless storefronts + CDP + Personalization (rules) | D6: 14 | E6: 0.333
A7: Phase 3: Scale (remaining 12–14 countries) | B7: Months 12–18 | C7: Full country migration + POS integration (top 200 stores) | D7: 6 | E7: 0.143
A8: Contingency Reserve | B8: Ongoing | C8: Unforeseen integration complexity / scope creep | D8: 4 | E8: 0.095
A9: TOTAL | D9: =SUM(D4:D8) | E9: =SUM(E4:E8)
